{
    "info": {
        "datast_nm": "식의약용 자생식물 분석 데이터",
        "datast_detail": "식의약용 자생식물 60종별로 식물종분류를 판별(인식)하기 위한 식물의 부위별(꽃, 열매, 잎앞면, 잎뒷면) AI 학습데이터",
        "wd_plnt_idntfr": 160
    },
    "images": {
        "image_file_id": "CR160_03_11290056",
        "image_file_nm": "CR160_03_11290056.jpg",
        "file_stre_cours": "\\식의약용 자생식물 분석 데이터\\03\\160\\CR160_03_11290056.jpg",
        "rsoltn": "1610, 1610",
        "region_nm": "한라수목원",
        "region_type": "평지",
        "plant_part": "열매",
        "grwh_step_nm": " ",
        "image_file_frmat": "JPG",
        "image_potogrf_dt": "2021-11-25 11:21:20"
    },
    "annotations": {
        "antn_id": 3701242,
        "antn_ty": "POLYGON",
        "object_class_lclas_code": "01",
        "object_class_mlsft_code": 160,
        "object_class_sclas_code": "03",
        "object_class_lclas_nm": "목본",
        "object_class_mlsft_nm": "꽝꽝나무",
        "object_class_sclas_nm": "열매",
        "pyn_xcrdnt": "982,962,940,879,778,694,657,611,556,518,485,463,462,465,477,503,546,578,580,594,614,677,721,772,779,832,903,949,1007,1083,1129,1152,1173,1180,1184,1179,1153,1117,1052,1031,1021,1012,986",
        "pyn_ycrdnt": "490,475,480,468,458,474,486,508,554,599,665,741,778,821,882,940,1000,1034,1042,1069,1085,1129,1144,1141,1138,1153,1153,1144,1119,1063,1007,959,907,867,830,750,671,613,552,539,512,494,493"
    },
    "plants": {
        "wd_plnt_nm": "꽝꽝나무",
        "scientific_nm": "Ilex crenata",
        "woody_herbal": "1",
        "edible_yn": "Y",
        "edible_part": "뿌리, 줄기(제한 사용)",
        "acquisition_term": "11월",
        "efficacy": "항염증|면역증진|항산화",
        "efficacy_ncl": "분석 진행중",
        "nutrient": "분석 진행중"
    },
    "ingredient": {
        "irdnt_nm": "분석 진행중",
        "irdnt_ncl": "분석 진행중",
        "irdnt_chmcls_strct": " ",
        "irdnt_anals_instlm": "제주산학융합원"
    },
    "licenses": {
        "lcnse_nm": "CC-BY-SA"
    }
}