{
    "info": {
        "datast_nm": "식의약용 자생식물 분석 데이터",
        "datast_detail": "식의약용 자생식물 60종별로 식물종분류를 판별(인식)하기 위한 식물의 부위별(꽃, 열매, 잎앞면, 잎뒷면) AI 학습데이터",
        "wd_plnt_idntfr": 160
    },
    "images": {
        "image_file_id": "CR160_03_11290537",
        "image_file_nm": "CR160_03_11290537.jpg",
        "file_stre_cours": "\\식의약용 자생식물 분석 데이터\\03\\160\\CR160_03_11290537.jpg",
        "rsoltn": "1915, 1915",
        "region_nm": "한라수목원",
        "region_type": "평지",
        "plant_part": "열매",
        "grwh_step_nm": " ",
        "image_file_frmat": "JPG",
        "image_potogrf_dt": "2021-11-25 11:32:25"
    },
    "annotations": {
        "antn_id": 3700410,
        "antn_ty": "POLYGON",
        "object_class_lclas_code": "01",
        "object_class_mlsft_code": 160,
        "object_class_sclas_code": "03",
        "object_class_lclas_nm": "목본",
        "object_class_mlsft_nm": "꽝꽝나무",
        "object_class_sclas_nm": "열매",
        "pyn_xcrdnt": "1201,1240,1266,1296,1317,1348,1371,1389,1404,1422,1434,1441,1446,1451,1454,1451,1456,1456,1456,1463,1466,1463,1449,1442,1429,1422,1417,1412,1392,1380,1364,1324,1291,1261,1248,1226,1215,1195,1171,1149,1109,1071,1031,977,945,877,840,799,764,738,697,670,643,631,619,610,606,607,610,632,658,684,702,769,795,827,869,902,927,960,1009,1045,1061,1100,1149",
        "pyn_ycrdnt": "397,416,430,449,468,499,526,551,580,619,650,671,699,735,766,831,843,853,864,872,883,894,923,929,932,946,954,957,994,1016,1038,1087,1118,1143,1154,1164,1174,1186,1200,1209,1223,1231,1239,1238,1235,1221,1205,1182,1160,1137,1096,1059,1005,975,943,890,844,791,719,658,604,566,542,477,456,438,416,402,394,384,375,375,373,374,381"
    },
    "plants": {
        "wd_plnt_nm": "꽝꽝나무",
        "scientific_nm": "Ilex crenata",
        "woody_herbal": "1",
        "edible_yn": "Y",
        "edible_part": "뿌리, 줄기(제한 사용)",
        "acquisition_term": "11월",
        "efficacy": "항염증|면역증진|항산화",
        "efficacy_ncl": "분석 진행중",
        "nutrient": "분석 진행중"
    },
    "ingredient": {
        "irdnt_nm": "분석 진행중",
        "irdnt_ncl": "분석 진행중",
        "irdnt_chmcls_strct": " ",
        "irdnt_anals_instlm": "제주산학융합원"
    },
    "licenses": {
        "lcnse_nm": "CC-BY-SA"
    }
}