{
    "info": {
        "datast_nm": "식의약용 자생식물 분석 데이터",
        "datast_detail": "식의약용 자생식물 60종별로 식물종분류를 판별(인식)하기 위한 식물의 부위별(꽃, 열매, 잎앞면, 잎뒷면) AI 학습데이터",
        "wd_plnt_idntfr": 160
    },
    "images": {
        "image_file_id": "CR160_03_11290618",
        "image_file_nm": "CR160_03_11290618.jpg",
        "file_stre_cours": "\\식의약용 자생식물 분석 데이터\\03\\160\\CR160_03_11290618.jpg",
        "rsoltn": "1930, 1930",
        "region_nm": "한라수목원",
        "region_type": "평지",
        "plant_part": "열매",
        "grwh_step_nm": " ",
        "image_file_frmat": "JPG",
        "image_potogrf_dt": "2021-11-25 11:34:26"
    },
    "annotations": {
        "antn_id": 3700642,
        "antn_ty": "POLYGON",
        "object_class_lclas_code": "01",
        "object_class_mlsft_code": 160,
        "object_class_sclas_code": "03",
        "object_class_lclas_nm": "목본",
        "object_class_mlsft_nm": "꽝꽝나무",
        "object_class_sclas_nm": "열매",
        "pyn_xcrdnt": "1399,1368,1331,1257,1198,1104,1024,936,853,782,722,673,653,641,650,669,721,745,816,897,983,1064,1152,1266,1317,1378,1429,1460,1484,1489,1480,1464,1470,1475,1477,1492",
        "pyn_ycrdnt": "1017,1037,1040,1106,1139,1165,1166,1151,1123,1068,1002,914,840,725,638,578,504,470,433,396,365,354,357,382,409,459,524,585,653,722,778,824,838,880,905,921"
    },
    "plants": {
        "wd_plnt_nm": "꽝꽝나무",
        "scientific_nm": "Ilex crenata",
        "woody_herbal": "1",
        "edible_yn": "Y",
        "edible_part": "뿌리, 줄기(제한 사용)",
        "acquisition_term": "11월",
        "efficacy": "항염증|면역증진|항산화",
        "efficacy_ncl": "분석 진행중",
        "nutrient": "분석 진행중"
    },
    "ingredient": {
        "irdnt_nm": "분석 진행중",
        "irdnt_ncl": "분석 진행중",
        "irdnt_chmcls_strct": " ",
        "irdnt_anals_instlm": "제주산학융합원"
    },
    "licenses": {
        "lcnse_nm": "CC-BY-SA"
    }
}