{
    "info": {
        "datast_nm": "식의약용 자생식물 분석 데이터",
        "datast_detail": "식의약용 자생식물 60종별로 식물종분류를 판별(인식)하기 위한 식물의 부위별(꽃, 열매, 잎앞면, 잎뒷면) AI 학습데이터",
        "wd_plnt_idntfr": "009"
    },
    "images": {
        "image_file_id": "CR009_05_51945",
        "image_file_nm": "CR009_05_51945.jpg",
        "file_stre_cours": "\\식의약용 자생식물 분석 데이터\\05\\009\\CR009_05_51945.jpg",
        "rsoltn": "1262, 1262",
        "region_nm": "성산",
        "region_type": "평지",
        "plant_part": "잎-뒷면",
        "grwh_step_nm": " ",
        "image_file_frmat": "JPG",
        "image_potogrf_dt": "2021-10-29 15:01:29"
    },
    "annotations": {
        "antn_id": 3579996,
        "antn_ty": "POLYGON",
        "object_class_lclas_code": "02",
        "object_class_mlsft_code": "009",
        "object_class_sclas_code": "05",
        "object_class_lclas_nm": "초본",
        "object_class_mlsft_nm": "메밀",
        "object_class_sclas_nm": "잎-뒷면",
        "pyn_xcrdnt": "427,397,373,345,314,275,243,213,199,175,166,168,178,202,235,267,326,477,502,523,607,701,735,777,843,909,979,1061,1091,1104,1104,1085,1027,977,931,887,850,807,778,770,765,765,792,803,810,813,814,819,815,814,814,810,797,779,763,715,678,649,627,608,584,560,547",
        "pyn_ycrdnt": "559,608,639,665,697,725,749,770,784,791,819,840,856,867,873,876,869,842,835,837,828,809,810,803,789,771,735,684,660,632,599,589,573,556,545,537,537,543,551,535,524,512,499,479,450,418,396,383,341,301,281,251,232,223,229,265,295,315,327,333,343,359,377"
    },
    "plants": {
        "wd_plnt_nm": "메밀",
        "scientific_nm": "Fagopyrum esculentum Moench, 1794.",
        "woody_herbal": "2",
        "edible_yn": "Y",
        "edible_part": "잎, 줄기, 꽃, 씨앗",
        "acquisition_term": "10월",
        "efficacy": "항염증|면역증진|항산화",
        "efficacy_ncl": "8.9|9.0|0.0",
        "nutrient": "15.1|15.8|15.2"
    },
    "ingredient": {
        "irdnt_nm": "6-Hydroxykaempferol-3-O-glucoside|Kaempferol 3-O-β-D-glucopyranoside|1-O-Caffeoyquinic acid|Cnidimol F|Procyanidin B8|Rhamnetin|1-Galloyl-glucose|QuinquenosideⅠ|5,7,8,3-Tetrahydroxy-3,4-dimethoxy flavone|3,5-Dihydroxybenzoic acid",
        "irdnt_ncl": "0.6|0.4|-0.3|0.5|-0.4|0.0|0.0|-0.2|0.4|0.5",
        "irdnt_chmcls_strct": " ",
        "irdnt_anals_instlm": "제주산학융합원"
    },
    "licenses": {
        "lcnse_nm": "CC-BY-SA"
    }
}