{
    "info": {
        "datast_nm": "식의약용 자생식물 분석 데이터",
        "datast_detail": "식의약용 자생식물 60종별로 식물종분류를 판별(인식)하기 위한 식물의 부위별(꽃, 열매, 잎앞면, 잎뒷면) AI 학습데이터",
        "wd_plnt_idntfr": "001"
    },
    "images": {
        "image_file_id": "CR001_03_11260673",
        "image_file_nm": "CR001_03_11260673.jpg",
        "file_stre_cours": "\\식의약용 자생식물 분석 데이터\\03\\001\\CR001_03_11260673.jpg",
        "rsoltn": "3024, 3024",
        "region_nm": "한라수목원",
        "region_type": "평지",
        "plant_part": "열매",
        "grwh_step_nm": " ",
        "image_file_frmat": "JPG",
        "image_potogrf_dt": "2021-11-25 11:10:21"
    },
    "annotations": {
        "antn_id": 3693216,
        "antn_ty": "POLYGON",
        "object_class_lclas_code": "01",
        "object_class_mlsft_code": "001",
        "object_class_sclas_code": "03",
        "object_class_lclas_nm": "목본",
        "object_class_mlsft_nm": "까마귀쪽나무",
        "object_class_sclas_nm": "열매",
        "pyn_xcrdnt": "1379,1355,1336,1328,1328,1301,1291,1276,1264,1261,1267,1262,1283,1318,1337,1344,1358,1375,1413,1444,1467,1483,1488,1500,1520,1542,1584,1618,1643,1669,1691,1720,1769,1825,1883,1952,2011,2064,2115,2151,2175,2205,2220,2239,2256,2269,2282,2293,2295,2292,2314,2324,2333,2338,2334,2325,2307,2290,2264,2234,2184,2155,2142,2133,2110,2081,2067,2055,2003,1949,1911,1869,1841,1821,1804,1784,1779,1762,1743,1729,1693,1653,1637,1591,1554,1512,1493,1473,1451,1431,1399",
        "pyn_ycrdnt": "870,861,859,866,868,876,878,893,909,922,940,959,1021,1079,1128,1171,1185,1224,1293,1342,1395,1427,1446,1522,1615,1692,1775,1821,1851,1872,1880,1870,1933,1992,2059,2115,2152,2180,2193,2193,2193,2191,2188,2195,2195,2191,2179,2166,2149,2132,2087,2053,2022,1965,1921,1853,1783,1731,1673,1622,1554,1519,1502,1470,1436,1404,1380,1369,1334,1289,1266,1249,1236,1230,1217,1213,1212,1202,1198,1197,1184,1172,1154,1102,1062,1011,973,944,910,894,875"
    },
    "plants": {
        "wd_plnt_nm": "까마귀쪽나무",
        "scientific_nm": "Litsea japonica (Thunb.) Juss., 1801.",
        "woody_herbal": "1",
        "edible_yn": "Y",
        "edible_part": "열매",
        "acquisition_term": "11월",
        "efficacy": "항염증|면역증진|항산화",
        "efficacy_ncl": "72.0|28.7|71.4",
        "nutrient": "16.2|15.9|16.0"
    },
    "ingredient": {
        "irdnt_nm": "Kaempferol-7-rhamnoside|chlorogenic acid|Questin|Chrysosplenetin B|Myricetin 3-O-glucoside|(E,E)-9-Oxooctadeca-10,12-dienoic acid|6-Hydroxykaempferol 3-glucoside|Luteolin-7-beta-neohesperidoside|lithospermic acid B|Trifolin",
        "irdnt_ncl": "-0.1|-1.9|-0.5|-0.3|-0.1|0.5|0.2|0.8|0.3|1.0",
        "irdnt_chmcls_strct": " ",
        "irdnt_anals_instlm": "제주산학융합원"
    },
    "licenses": {
        "lcnse_nm": "CC-BY-SA"
    }
}