{
    "info": {
        "datast_nm": "식의약용 자생식물 분석 데이터",
        "datast_detail": "식의약용 자생식물 60종별로 식물종분류를 판별(인식)하기 위한 식물의 부위별(꽃, 열매, 잎앞면, 잎뒷면) AI 학습데이터",
        "wd_plnt_idntfr": "022"
    },
    "images": {
        "image_file_id": "CR022_02_51782a",
        "image_file_nm": "CR022_02_51782a.jpg",
        "file_stre_cours": "\\식의약용 자생식물 분석 데이터\\02\\022\\CR022_02_51782a.jpg",
        "rsoltn": "301, 301",
        "region_nm": "농산물원종장",
        "region_type": "평지",
        "plant_part": "꽃",
        "grwh_step_nm": " ",
        "image_file_frmat": "JPG",
        "image_potogrf_dt": "2021-10-01 14:19:04"
    },
    "annotations": {
        "antn_id": 3524943,
        "antn_ty": "POLYGON",
        "object_class_lclas_code": "02",
        "object_class_mlsft_code": "022",
        "object_class_sclas_code": "02",
        "object_class_lclas_nm": "초본",
        "object_class_mlsft_nm": "큰조롱",
        "object_class_sclas_nm": "꽃",
        "pyn_xcrdnt": "296,282,271,259,254,244,235,229,219,210,204,205,204,200,194,189,185,182,177,168,163,161,154,142,139,134,130,126,128,133,133,132,126,125,119,117,111,103,98,100,104,102,95,92,87,79,76,77,82,85,91,99,100,91,82,79,76,69,63,59,56,54,47,44,45,41,43,50,55,56,63,67,72,74,72,77,80,83,80,81,86,93,104,112,111,109,107,108,112,111,107,114,123,132,132,132,136,141,146,153,157,163,166,171,176,177,183,188,187,193,195,198,199,204,210,213,215,223,225,230,233,235,240,243,246,251,253,253,252,254,256,260,262,260,258,261,263,265,266,270,268,265,262,260,264,268,269,264,253,246,243,237,236,241,243,242,248,255,256,256,257,260,265,269,270,277,286,297",
        "pyn_ycrdnt": "238,231,226,227,232,232,229,234,237,236,232,226,219,217,218,217,219,226,228,226,223,219,226,223,217,216,215,212,205,204,200,197,202,194,193,189,187,186,178,169,164,162,163,160,157,160,155,152,146,137,134,133,130,128,126,123,120,121,122,121,117,113,109,100,94,89,87,89,87,83,82,83,90,94,98,96,96,93,86,74,65,65,72,76,81,89,96,100,101,109,112,122,128,132,123,116,115,118,114,116,114,118,112,109,113,119,119,124,126,130,132,131,122,119,120,122,123,114,108,109,113,109,110,113,110,109,113,118,122,124,119,121,123,125,128,130,133,133,136,140,145,147,147,150,155,159,163,164,161,156,153,154,161,165,172,176,180,185,190,197,201,201,198,201,206,210,215,222"
    },
    "plants": {
        "wd_plnt_nm": "큰조롱",
        "scientific_nm": "Cynanchum wilfordii (Maxim.) Hemsl., 1889.",
        "woody_herbal": "2",
        "edible_yn": "Y",
        "edible_part": "뿌리(물추출물에 한함)",
        "acquisition_term": "10월",
        "efficacy": "항염증|면역증진|항산화",
        "efficacy_ncl": "0.0|0.0|0.0",
        "nutrient": "15.1|15.6|16.0"
    },
    "ingredient": {
        "irdnt_nm": "Polygoacetophenoside|Kaempferol 3-O-β-D-glucopyranoside|Quercetin-3-O-xyloside|Quercetin-3-O-α-D-glucuronide|Kaempferol-3-O-β-D-glucuronide|Catechin-3-O-gallate|Bruceine H|Procyanidin B1|Sanleng acid|1-Galloyl-glucose",
        "irdnt_ncl": "2.8|0.4|0.4|-0.3|0.2|0.0|0.6|0.0|0.2|0.6",
        "irdnt_chmcls_strct": " ",
        "irdnt_anals_instlm": "제주산학융합원"
    },
    "licenses": {
        "lcnse_nm": "CC-BY-SA"
    }
}