{
    "info": {
        "datast_nm": "식의약용 자생식물 분석 데이터",
        "datast_detail": "식의약용 자생식물 60종별로 식물종분류를 판별(인식)하기 위한 식물의 부위별(꽃, 열매, 잎앞면, 잎뒷면) AI 학습데이터",
        "wd_plnt_idntfr": "009"
    },
    "images": {
        "image_file_id": "CR009_02_51166",
        "image_file_nm": "CR009_02_51166.jpg",
        "file_stre_cours": "\\식의약용 자생식물 분석 데이터\\02\\009\\CR009_02_51166.jpg",
        "rsoltn": "1033, 1033",
        "region_nm": "동광리",
        "region_type": "평지",
        "plant_part": "꽃",
        "grwh_step_nm": " ",
        "image_file_frmat": "JPG",
        "image_potogrf_dt": "2021-10-08 14:35:01"
    },
    "annotations": {
        "antn_id": 3538815,
        "antn_ty": "POLYGON",
        "object_class_lclas_code": "02",
        "object_class_mlsft_code": "009",
        "object_class_sclas_code": "02",
        "object_class_lclas_nm": "초본",
        "object_class_mlsft_nm": "메밀",
        "object_class_sclas_nm": "꽃",
        "pyn_xcrdnt": "429,443,463,463,483,495,489,497,485,514,520,566,553,551,570,596,609,621,663,676,701,712,742,753,782,814,829,823,846,840,789,793,825,832,843,830,809,793,789,782,779,762,781,766,773,769,770,763,726,713,696,679,713,709,722,724,709,707,712,700,681,662,651,657,643,631,611,590,582,565,562,546,527,522,520,503,493,465,450,427,427,486,487,477,460,440,417,405,403,410,401,389,383,367,370,369,407,403,429,424,412,394,385,372,367,373,349,330,321,317,300,269,257,257,232,226,197,191,180,164,149,159,169,133,116,119,109,129,139,143,203,203,243,243,207,203,200,221,253,273,293,307,320,336,333,335,341,355,363,354,369,375,399,426,434",
        "pyn_ycrdnt": "329,319,321,335,347,328,305,298,266,258,229,246,225,193,181,147,147,122,132,104,105,98,109,138,165,165,186,205,218,239,259,271,286,309,333,364,369,383,399,413,432,449,482,491,514,558,599,615,602,589,615,625,643,665,686,716,721,773,804,819,817,809,821,838,848,864,875,877,888,885,864,878,868,886,907,911,903,909,879,879,862,803,793,786,811,803,812,786,755,743,723,729,706,689,673,641,613,594,573,561,568,555,536,541,538,565,575,579,572,582,572,572,564,548,545,537,536,521,507,501,475,461,438,436,418,409,385,362,361,335,364,368,379,371,348,317,289,289,267,278,276,288,279,289,325,344,351,361,366,328,307,291,279,287,301"
    },
    "plants": {
        "wd_plnt_nm": "메밀",
        "scientific_nm": "Fagopyrum esculentum Moench, 1794.",
        "woody_herbal": "2",
        "edible_yn": "Y",
        "edible_part": "잎, 줄기, 꽃, 씨앗",
        "acquisition_term": "10월",
        "efficacy": "항염증|면역증진|항산화",
        "efficacy_ncl": "8.9|9.0|0.0",
        "nutrient": "15.1|15.8|15.2"
    },
    "ingredient": {
        "irdnt_nm": "6-Hydroxykaempferol-3-O-glucoside|Kaempferol 3-O-β-D-glucopyranoside|1-O-Caffeoyquinic acid|Cnidimol F|Procyanidin B8|Rhamnetin|1-Galloyl-glucose|QuinquenosideⅠ|5,7,8,3-Tetrahydroxy-3,4-dimethoxy flavone|3,5-Dihydroxybenzoic acid",
        "irdnt_ncl": "0.6|0.4|-0.3|0.5|-0.4|0.0|0.0|-0.2|0.4|0.5",
        "irdnt_chmcls_strct": " ",
        "irdnt_anals_instlm": "제주산학융합원"
    },
    "licenses": {
        "lcnse_nm": "CC-BY-SA"
    }
}