{
    "info": {
        "datast_nm": "식의약용 자생식물 분석 데이터",
        "datast_detail": "식의약용 자생식물 60종별로 식물종분류를 판별(인식)하기 위한 식물의 부위별(꽃, 열매, 잎앞면, 잎뒷면) AI 학습데이터",
        "wd_plnt_idntfr": 153
    },
    "images": {
        "image_file_id": "CR153_03_12010698",
        "image_file_nm": "CR153_03_12010698.jpg",
        "file_stre_cours": "\\식의약용 자생식물 분석 데이터\\03\\153\\CR153_03_12010698.jpg",
        "rsoltn": "1514, 1514",
        "region_nm": "한라수목원",
        "region_type": "평지",
        "plant_part": "열매",
        "grwh_step_nm": " ",
        "image_file_frmat": "JPG",
        "image_potogrf_dt": "2021-11-25 10:26:27"
    },
    "annotations": {
        "antn_id": 3690343,
        "antn_ty": "POLYGON",
        "object_class_lclas_code": "01",
        "object_class_mlsft_code": 153,
        "object_class_sclas_code": "03",
        "object_class_lclas_nm": "목본",
        "object_class_mlsft_nm": "백량금",
        "object_class_sclas_nm": "열매",
        "pyn_xcrdnt": "1506,1453,1440,1406,1395,1354,1318,1304,1282,1267,1250,1234,1214,1193,1169,1154,1144,1106,1085,1069,1057,1025,1012,980,959,918,899,887,858,851,836,843,795,756,691,620,611,596,583,578,573,570,565,560,561,565,570,573,578,575,588,593,601,642,676,686,696,720,733,779,791,804,818,840,853,859,869,879,899,913,925,948,958,962,982,985,994,997,1002,1008,1013,1015,1021,1016,1028,1033,1030,1025,1010,998,995,987,990,984,984,997,1025,1034,1157,1239,1270,1298,1309,1327,1355,1377,1404,1422,1437,1455,1506",
        "pyn_ycrdnt": "1434,1399,1390,1362,1354,1321,1293,1285,1265,1255,1242,1231,1214,1196,1175,1165,1157,1123,1106,1093,1084,1054,1043,1016,998,964,958,977,994,1012,1013,990,1008,997,977,921,907,881,859,843,831,809,795,768,705,676,661,650,642,625,624,614,602,560,535,529,525,517,512,512,511,511,512,516,517,519,524,529,540,552,560,575,589,596,620,629,642,656,665,683,696,709,735,756,755,759,768,779,807,822,833,849,863,874,890,908,939,954,1075,1154,1180,1205,1214,1228,1252,1268,1293,1306,1318,1331,1372"
    },
    "plants": {
        "wd_plnt_nm": "백량금",
        "scientific_nm": "Ardisia crenata",
        "woody_herbal": "1",
        "edible_yn": "N",
        "edible_part": "N/A",
        "acquisition_term": "11월",
        "efficacy": "항염증|면역증진|항산화",
        "efficacy_ncl": "분석 진행중",
        "nutrient": "분석 진행중"
    },
    "ingredient": {
        "irdnt_nm": "분석 진행중",
        "irdnt_ncl": "분석 진행중",
        "irdnt_chmcls_strct": " ",
        "irdnt_anals_instlm": "제주산학융합원"
    },
    "licenses": {
        "lcnse_nm": "CC-BY-SA"
    }
}