{
    "info": {
        "datast_nm": "식의약용 자생식물 분석 데이터",
        "datast_detail": "식의약용 자생식물 60종별로 식물종분류를 판별(인식)하기 위한 식물의 부위별(꽃, 열매, 잎앞면, 잎뒷면) AI 학습데이터",
        "wd_plnt_idntfr": 153
    },
    "images": {
        "image_file_id": "CR153_03_12010442",
        "image_file_nm": "CR153_03_12010442.jpg",
        "file_stre_cours": "\\식의약용 자생식물 분석 데이터\\03\\153\\CR153_03_12010442.jpg",
        "rsoltn": "1268, 1268",
        "region_nm": "한라수목원",
        "region_type": "평지",
        "plant_part": "열매",
        "grwh_step_nm": " ",
        "image_file_frmat": "JPG",
        "image_potogrf_dt": "2021-11-25 10:05:01"
    },
    "annotations": {
        "antn_id": 3692899,
        "antn_ty": "POLYGON",
        "object_class_lclas_code": "01",
        "object_class_mlsft_code": 153,
        "object_class_sclas_code": "03",
        "object_class_lclas_nm": "목본",
        "object_class_mlsft_nm": "백량금",
        "object_class_sclas_nm": "열매",
        "pyn_xcrdnt": "380,381,387,388,389,392,398,421,428,441,451,458,491,500,504,510,514,521,535,539,548,559,565,578,588,598,606,622,632,633,669,677,685,695,703,710,718,725,736,769,777,788,792,795,799,796,792,788,784,780,773,748,727,716,644,603,546,513,491,489,487,491,493,498,500,503,499,518,522,548,547,531,524,521,498,493,491,487,480,474,465,458,451,443,436,426,421,407,398,389,381,362,361,363,377",
        "pyn_ycrdnt": "210,208,208,210,210,212,223,256,267,288,300,311,358,371,380,391,399,407,424,432,444,461,469,496,509,517,511,509,504,511,514,517,525,529,532,536,539,543,547,577,589,607,614,633,658,696,710,725,732,740,750,781,801,803,833,828,813,777,735,722,683,657,644,637,626,615,609,592,581,557,544,509,495,487,446,437,430,422,409,400,387,377,366,355,344,332,322,302,289,277,266,245,234,221,210"
    },
    "plants": {
        "wd_plnt_nm": "백량금",
        "scientific_nm": "Ardisia crenata",
        "woody_herbal": "1",
        "edible_yn": "N",
        "edible_part": "N/A",
        "acquisition_term": "11월",
        "efficacy": "항염증|면역증진|항산화",
        "efficacy_ncl": "분석 진행중",
        "nutrient": "분석 진행중"
    },
    "ingredient": {
        "irdnt_nm": "분석 진행중",
        "irdnt_ncl": "분석 진행중",
        "irdnt_chmcls_strct": " ",
        "irdnt_anals_instlm": "제주산학융합원"
    },
    "licenses": {
        "lcnse_nm": "CC-BY-SA"
    }
}