{
    "info": {
        "datast_nm": "식의약용 자생식물 분석 데이터",
        "datast_detail": "식의약용 자생식물 60종별로 식물종분류를 판별(인식)하기 위한 식물의 부위별(꽃, 열매, 잎앞면, 잎뒷면) AI 학습데이터",
        "wd_plnt_idntfr": "041"
    },
    "images": {
        "image_file_id": "CR041_02_51567",
        "image_file_nm": "CR041_02_51567.jpg",
        "file_stre_cours": "\\식의약용 자생식물 분석 데이터\\02\\041\\CR041_02_51567.jpg",
        "rsoltn": "2096, 2096",
        "region_nm": "한라수목원",
        "region_type": "경사지",
        "plant_part": "꽃",
        "grwh_step_nm": " ",
        "image_file_frmat": "JPG",
        "image_potogrf_dt": "2021-10-20 14:09:44"
    },
    "annotations": {
        "antn_id": 3586359,
        "antn_ty": "POLYGON",
        "object_class_lclas_code": "01",
        "object_class_mlsft_code": "041",
        "object_class_sclas_code": "02",
        "object_class_lclas_nm": "목본",
        "object_class_mlsft_nm": "참꽃나무",
        "object_class_sclas_nm": "꽃",
        "pyn_xcrdnt": "1337,1300,1289,1272,1254,1201,1129,1076,1069,1053,1039,1017,995,854,807,802,838,864,816,812,779,764,794,836,877,905,931,939,954,972,1005,1021,1037,1046,1083,1132,1178,1209,1245,1253,1257,1263,1292,1350,1398,1453,1491,1533,1568,1607,1610,1598,1598,1568,1541,1515,1469,1451,1556,1592,1637,1674,1701,1715,1714,1701,1682,1648,1635,1587,1541,1497,1449,1393,1371",
        "pyn_ycrdnt": "1398,1436,1461,1462,1482,1507,1531,1509,1467,1453,1352,1323,1236,1189,1192,1175,1069,1004,914,887,856,823,758,706,659,627,613,595,587,553,547,554,606,624,566,501,460,442,439,455,472,436,401,394,383,366,386,433,485,554,618,646,664,727,779,817,852,863,897,917,966,998,1055,1086,1141,1196,1207,1213,1209,1243,1263,1272,1285,1302,1311"
    },
    "plants": {
        "wd_plnt_nm": "참꽃나무",
        "scientific_nm": "Rhododendron weyrichii Maxim., 1871.",
        "woody_herbal": "1",
        "edible_yn": "N",
        "edible_part": "N/A",
        "acquisition_term": "10월",
        "efficacy": "항염증|면역증진|항산화",
        "efficacy_ncl": "0.0|0.0|0.0",
        "nutrient": "15.2|15.2|15.4"
    },
    "ingredient": {
        "irdnt_nm": "6-Hydroxykaempferol-3-O-glucoside|21-O-Methyl toosendanopentaol|20(S)-Ginsenoside Rh2 (Ginsenoside Rh2)|3β-O-trans-p-Coumaroyl alphitolic acid|Chlorogenic acid|1-O-Caffeoyquinic acid|Kaempferol-3-Glucoside-2'-p-coumaroyl|Procyanidin B8|Quercetin-3-O-xyloside|Neocomplanoside",
        "irdnt_ncl": "0.2|1.0|0.2|-0.5|-0.3|0.1|0.9|0.2|0.0|0.2",
        "irdnt_chmcls_strct": " ",
        "irdnt_anals_instlm": "제주산학융합원"
    },
    "licenses": {
        "lcnse_nm": "CC-BY-SA"
    }
}