{
    "info": {
        "datast_nm": "식의약용 자생식물 분석 데이터",
        "datast_detail": "식의약용 자생식물 60종별로 식물종분류를 판별(인식)하기 위한 식물의 부위별(꽃, 열매, 잎앞면, 잎뒷면) AI 학습데이터",
        "wd_plnt_idntfr": "041"
    },
    "images": {
        "image_file_id": "CR041_02_52272",
        "image_file_nm": "CR041_02_52272.jpg",
        "file_stre_cours": "\\식의약용 자생식물 분석 데이터\\02\\041\\CR041_02_52272.jpg",
        "rsoltn": "1389, 1389",
        "region_nm": "한라수목원",
        "region_type": "경사지",
        "plant_part": "꽃",
        "grwh_step_nm": " ",
        "image_file_frmat": "JPG",
        "image_potogrf_dt": "2021-10-20 15:53:53"
    },
    "annotations": {
        "antn_id": 3566983,
        "antn_ty": "POLYGON",
        "object_class_lclas_code": "01",
        "object_class_mlsft_code": "041",
        "object_class_sclas_code": "02",
        "object_class_lclas_nm": "목본",
        "object_class_mlsft_nm": "참꽃나무",
        "object_class_sclas_nm": "꽃",
        "pyn_xcrdnt": "371,351,325,289,265,230,190,172,159,150,148,156,165,188,204,221,236,263,285,304,327,356,391,421,451,495,527,544,545,552,563,595,600,627,652,670,697,760,795,807,819,841,858,861,871,876,882,894,927,1008,1051,1082,1100,1111,1118,1120,1109,1100,1096,1099,1097,1085,1068,1044,1023,1040,1055,1065,1082,1102,1112,1118,1116,1114,1110,1101,1054,1048,1041,1019,1000,973,947,914,887,864,846,830,810,797,781,755,739,729,717,704,690,674,659,634,617,591,576,550,534,510,489,462,431,408,386,367,353,338,315,304,297,291,293,298,309,314,317,316,315,320,329,345",
        "pyn_ycrdnt": "454,477,497,518,521,529,532,526,526,534,551,583,610,652,682,702,714,724,730,737,741,741,733,725,714,699,681,669,684,716,743,777,795,816,833,842,855,890,871,885,896,897,889,869,795,776,703,674,663,660,646,646,643,638,631,619,603,589,574,554,544,527,519,501,485,478,469,456,422,377,351,330,307,273,264,260,266,271,271,257,248,241,238,232,226,225,222,225,232,239,241,253,265,277,291,301,317,336,349,378,339,295,268,239,230,228,231,237,239,230,226,230,226,225,227,227,236,249,261,272,282,303,328,355,379,395,410,427"
    },
    "plants": {
        "wd_plnt_nm": "참꽃나무",
        "scientific_nm": "Rhododendron weyrichii Maxim., 1871.",
        "woody_herbal": "1",
        "edible_yn": "N",
        "edible_part": "N/A",
        "acquisition_term": "10월",
        "efficacy": "항염증|면역증진|항산화",
        "efficacy_ncl": "0.0|0.0|0.0",
        "nutrient": "15.2|15.2|15.4"
    },
    "ingredient": {
        "irdnt_nm": "6-Hydroxykaempferol-3-O-glucoside|21-O-Methyl toosendanopentaol|20(S)-Ginsenoside Rh2 (Ginsenoside Rh2)|3β-O-trans-p-Coumaroyl alphitolic acid|Chlorogenic acid|1-O-Caffeoyquinic acid|Kaempferol-3-Glucoside-2'-p-coumaroyl|Procyanidin B8|Quercetin-3-O-xyloside|Neocomplanoside",
        "irdnt_ncl": "0.2|1.0|0.2|-0.5|-0.3|0.1|0.9|0.2|0.0|0.2",
        "irdnt_chmcls_strct": " ",
        "irdnt_anals_instlm": "제주산학융합원"
    },
    "licenses": {
        "lcnse_nm": "CC-BY-SA"
    }
}