{
    "info": {
        "datast_nm": "식의약용 자생식물 분석 데이터",
        "datast_detail": "식의약용 자생식물 60종별로 식물종분류를 판별(인식)하기 위한 식물의 부위별(꽃, 열매, 잎앞면, 잎뒷면) AI 학습데이터",
        "wd_plnt_idntfr": "041"
    },
    "images": {
        "image_file_id": "CR041_02_51991",
        "image_file_nm": "CR041_02_51991.jpg",
        "file_stre_cours": "\\식의약용 자생식물 분석 데이터\\02\\041\\CR041_02_51991.jpg",
        "rsoltn": "1503, 1503",
        "region_nm": "한라수목원",
        "region_type": "경사지",
        "plant_part": "꽃",
        "grwh_step_nm": " ",
        "image_file_frmat": "JPG",
        "image_potogrf_dt": "2021-10-20 15:43:04"
    },
    "annotations": {
        "antn_id": 3566368,
        "antn_ty": "POLYGON",
        "object_class_lclas_code": "01",
        "object_class_mlsft_code": "041",
        "object_class_sclas_code": "02",
        "object_class_lclas_nm": "목본",
        "object_class_mlsft_nm": "참꽃나무",
        "object_class_sclas_nm": "꽃",
        "pyn_xcrdnt": "368,395,404,385,374,318,318,307,303,329,433,512,561,630,724,819,949,986,1079,1106,1202,1245,1271,1305,1306,1280,1276,1245,1230,1137,1091,1029,911,889,879,846,824,787,744,672,652,584,549,505,474,442,371,372,360,373,373,346,354",
        "pyn_ycrdnt": "636,708,786,774,746,747,778,922,975,997,1019,1028,1004,995,960,943,910,928,870,822,756,708,711,617,523,483,458,432,442,398,386,401,388,286,237,249,273,294,326,241,235,164,158,205,223,222,277,299,339,369,406,423,568"
    },
    "plants": {
        "wd_plnt_nm": "참꽃나무",
        "scientific_nm": "Rhododendron weyrichii Maxim., 1871.",
        "woody_herbal": "1",
        "edible_yn": "N",
        "edible_part": "N/A",
        "acquisition_term": "10월",
        "efficacy": "항염증|면역증진|항산화",
        "efficacy_ncl": "0.0|0.0|0.0",
        "nutrient": "15.2|15.2|15.4"
    },
    "ingredient": {
        "irdnt_nm": "6-Hydroxykaempferol-3-O-glucoside|21-O-Methyl toosendanopentaol|20(S)-Ginsenoside Rh2 (Ginsenoside Rh2)|3β-O-trans-p-Coumaroyl alphitolic acid|Chlorogenic acid|1-O-Caffeoyquinic acid|Kaempferol-3-Glucoside-2'-p-coumaroyl|Procyanidin B8|Quercetin-3-O-xyloside|Neocomplanoside",
        "irdnt_ncl": "0.2|1.0|0.2|-0.5|-0.3|0.1|0.9|0.2|0.0|0.2",
        "irdnt_chmcls_strct": " ",
        "irdnt_anals_instlm": "제주산학융합원"
    },
    "licenses": {
        "lcnse_nm": "CC-BY-SA"
    }
}