{
    "info": {
        "datast_nm": "식의약용 자생식물 분석 데이터",
        "datast_detail": "식의약용 자생식물 60종별로 식물종분류를 판별(인식)하기 위한 식물의 부위별(꽃, 열매, 잎앞면, 잎뒷면) AI 학습데이터",
        "wd_plnt_idntfr": "046"
    },
    "images": {
        "image_file_id": "CR046_03_54636",
        "image_file_nm": "CR046_03_54636.jpg",
        "file_stre_cours": "\\식의약용 자생식물 분석 데이터\\03\\046\\CR046_03_54636.jpg",
        "rsoltn": "793, 793",
        "region_nm": "농산물원종장",
        "region_type": "평지",
        "plant_part": "열매",
        "grwh_step_nm": " ",
        "image_file_frmat": "JPG",
        "image_potogrf_dt": "2021-10-01 14:51:52"
    },
    "annotations": {
        "antn_id": 3516254,
        "antn_ty": "POLYGON",
        "object_class_lclas_code": "01",
        "object_class_mlsft_code": "046",
        "object_class_sclas_code": "03",
        "object_class_lclas_nm": "목본",
        "object_class_mlsft_nm": "황근",
        "object_class_sclas_nm": "열매",
        "pyn_xcrdnt": "613,590,540,499,478,462,443,432,434,429,434,438,456,474,477,450,421,372,341,305,262,237,235,245,250,255,240,207,189,177,169,155,151,157,168,177,188,206,229,216,220,228,234,235,231,210,197,194,203,212,229,261,271,284,304,336,348,350,362,375,386,393,386,379,372,377,398,413,433,452,470,496,525,545,566,593,607,608,611,607,605,613,610,616,611,619,635,639,636,629,618",
        "pyn_ycrdnt": "304,281,244,212,173,147,130,138,150,174,202,216,229,236,239,239,237,240,242,230,204,198,212,231,262,276,274,265,268,271,273,271,274,284,285,290,313,319,334,357,377,391,407,416,423,435,447,464,465,462,461,458,468,496,514,524,531,536,549,555,556,553,541,532,516,514,520,530,540,548,551,551,551,550,533,506,493,470,464,457,448,445,430,427,411,409,409,407,356,333,309"
    },
    "plants": {
        "wd_plnt_nm": "황근",
        "scientific_nm": "Hibiscus hamabo Siebold & Zucc., 1841.",
        "woody_herbal": "1",
        "edible_yn": "N",
        "edible_part": "N/A",
        "acquisition_term": "10월",
        "efficacy": "항염증|면역증진|항산화",
        "efficacy_ncl": "41.1|13.3|0.0",
        "nutrient": "15.0|15.4|15.6"
    },
    "ingredient": {
        "irdnt_nm": "Procyanidin B1|(E,E)-9-oxooctadeca-10,12-dienoic acid|Quinquenoside I|Tianshic acid|Kaempferol-3-Glucoside-2-p-coumaroyl|6-Hydroxykaempferol-3-O-glucoside|Vernolic acid|Acrinidioionoside|Decaffeoylverbascoside|Glucosyringic acid",
        "irdnt_ncl": "-0.1|-0.1|0.7|0.9|-0.4|-0.4|0.6|-0.5|0.3|-0.5",
        "irdnt_chmcls_strct": " ",
        "irdnt_anals_instlm": "제주산학융합원"
    },
    "licenses": {
        "lcnse_nm": "CC-BY-SA"
    }
}