{
    "info": {
        "datast_nm": "식의약용 자생식물 분석 데이터",
        "datast_detail": "식의약용 자생식물 60종별로 식물종분류를 판별(인식)하기 위한 식물의 부위별(꽃, 열매, 잎앞면, 잎뒷면) AI 학습데이터",
        "wd_plnt_idntfr": "046"
    },
    "images": {
        "image_file_id": "CR046_03_55171",
        "image_file_nm": "CR046_03_55171.jpg",
        "file_stre_cours": "\\식의약용 자생식물 분석 데이터\\03\\046\\CR046_03_55171.jpg",
        "rsoltn": "689, 689",
        "region_nm": "농산물원종장",
        "region_type": "평지",
        "plant_part": "열매",
        "grwh_step_nm": " ",
        "image_file_frmat": "JPG",
        "image_potogrf_dt": "2021-10-01 16:34:39"
    },
    "annotations": {
        "antn_id": 3525995,
        "antn_ty": "POLYGON",
        "object_class_lclas_code": "01",
        "object_class_mlsft_code": "046",
        "object_class_sclas_code": "03",
        "object_class_lclas_nm": "목본",
        "object_class_mlsft_nm": "황근",
        "object_class_sclas_nm": "열매",
        "pyn_xcrdnt": "574,572,575,555,534,514,499,502,527,540,553,562,564,563,553,540,528,515,500,473,438,412,382,341,338,330,300,269,265,257,245,225,209,205,206,224,240,229,221,226,215,213,201,201,198,188,176,175,164,146,131,117,92,88,79,76,68,68,85,92,119,128,143,152,161,162,211,242,257,258,272,275,281,290,296,296,296,290,290,311,342,348,353,360,365,360,352,351,351,366,394,422,425,425,422,404,388,384,387,404,445,467,490,507,536,547",
        "pyn_ycrdnt": "331,352,373,366,362,360,363,367,370,378,390,401,417,442,470,503,522,533,546,555,561,555,543,533,537,539,518,501,501,503,510,516,515,508,501,492,480,474,465,458,448,444,436,426,420,413,408,395,384,357,336,324,315,301,290,276,267,261,260,255,255,252,253,253,253,266,263,258,256,219,197,180,167,167,177,186,195,202,214,235,247,241,246,240,241,234,214,202,180,167,165,161,163,170,173,185,183,198,204,216,235,247,261,274,294,310"
    },
    "plants": {
        "wd_plnt_nm": "황근",
        "scientific_nm": "Hibiscus hamabo Siebold & Zucc., 1841.",
        "woody_herbal": "1",
        "edible_yn": "N",
        "edible_part": "N/A",
        "acquisition_term": "10월",
        "efficacy": "항염증|면역증진|항산화",
        "efficacy_ncl": "41.1|13.3|0.0",
        "nutrient": "15.0|15.4|15.6"
    },
    "ingredient": {
        "irdnt_nm": "Procyanidin B1|(E,E)-9-oxooctadeca-10,12-dienoic acid|Quinquenoside I|Tianshic acid|Kaempferol-3-Glucoside-2-p-coumaroyl|6-Hydroxykaempferol-3-O-glucoside|Vernolic acid|Acrinidioionoside|Decaffeoylverbascoside|Glucosyringic acid",
        "irdnt_ncl": "-0.1|-0.1|0.7|0.9|-0.4|-0.4|0.6|-0.5|0.3|-0.5",
        "irdnt_chmcls_strct": " ",
        "irdnt_anals_instlm": "제주산학융합원"
    },
    "licenses": {
        "lcnse_nm": "CC-BY-SA"
    }
}