{
    "info": {
        "datast_nm": "식의약용 자생식물 분석 데이터",
        "datast_detail": "식의약용 자생식물 60종별로 식물종분류를 판별(인식)하기 위한 식물의 부위별(꽃, 열매, 잎앞면, 잎뒷면) AI 학습데이터",
        "wd_plnt_idntfr": "040"
    },
    "images": {
        "image_file_id": "CR040_03_51774a",
        "image_file_nm": "CR040_03_51774a.jpg",
        "file_stre_cours": "\\식의약용 자생식물 분석 데이터\\03\\040\\CR040_03_51774a.jpg",
        "rsoltn": "641, 641",
        "region_nm": "제주특별자치도 제주시 용담동",
        "region_type": "평지",
        "plant_part": "열매",
        "grwh_step_nm": " ",
        "image_file_frmat": "JPG",
        "image_potogrf_dt": "2021-08-12 17:23:22"
    },
    "annotations": {
        "antn_id": 3422955,
        "antn_ty": "POLYGON",
        "object_class_lclas_code": "01",
        "object_class_mlsft_code": "040",
        "object_class_sclas_code": "03",
        "object_class_lclas_nm": "목본",
        "object_class_mlsft_nm": "순비기나무",
        "object_class_sclas_nm": "열매",
        "pyn_xcrdnt": "171,160,148,140,138,133,132,126,129,131,139,147,158,168,162,157,154,157,160,165,168,179,184,189,199,210,225,237,246,261,266,275,290,305,319,330,333,340,354,367,381,401,417,434,445,447,442,440,432,417,414,424,434,451,471,487,499,512,520,527,527,524,514,507,497,478,465,446,429,419,410,390,377,379,380,392,401,407,412,407,401,392,382,371,350,329,309,294,287,286,289,277,264,247,238,221,201,189,184",
        "pyn_ycrdnt": "230,228,232,242,252,259,259,274,290,305,317,329,338,342,355,363,373,379,394,406,417,429,435,440,444,446,450,448,446,450,455,461,467,466,465,463,474,485,495,501,504,504,502,489,470,448,425,412,402,396,389,383,389,393,392,391,381,377,357,342,326,311,297,290,283,277,276,277,283,290,296,290,285,270,260,245,231,220,201,185,173,161,151,147,139,144,153,166,180,200,210,194,186,181,184,185,189,199,209"
    },
    "plants": {
        "wd_plnt_nm": "순비기나무",
        "scientific_nm": "Vitex rotundifolia L. f., 1781.",
        "woody_herbal": "1",
        "edible_yn": "N",
        "edible_part": "N/A",
        "acquisition_term": "08월",
        "efficacy": "항염증|면역증진|항산화",
        "efficacy_ncl": "67.0|3.6|72.4",
        "nutrient": "15.3|15.2|15.0"
    },
    "ingredient": {
        "irdnt_nm": "Agnuside|Oxypaeoniflorin|Trifolin|Kaempferol 3-O-β-D-glucuronide|Cimicifugic acid B|Apigenin-7-O-acetyl-β-D-glucoside|20(S)-Ginsenoside Rh2|5,6,4-Trihydroxy-7,8-dimethoxyflavone",
        "irdnt_ncl": "-0.2|-0.1|-0.3|0.1|0.0|-0.4|-0.4|0.9",
        "irdnt_chmcls_strct": " ",
        "irdnt_anals_instlm": "제주산학융합원"
    },
    "licenses": {
        "lcnse_nm": "CC-BY-SA"
    }
}