{
    "info": {
        "datast_nm": "식의약용 자생식물 분석 데이터",
        "datast_detail": "식의약용 자생식물 60종별로 식물종분류를 판별(인식)하기 위한 식물의 부위별(꽃, 열매, 잎앞면, 잎뒷면) AI 학습데이터",
        "wd_plnt_idntfr": "043"
    },
    "images": {
        "image_file_id": "CR043_03_11240055",
        "image_file_nm": "CR043_03_11240055.jpg",
        "file_stre_cours": "\\식의약용 자생식물 분석 데이터\\03\\043\\CR043_03_11240055.jpg",
        "rsoltn": "3024, 3024",
        "region_nm": "한라수목원",
        "region_type": "평지",
        "plant_part": "열매",
        "grwh_step_nm": " ",
        "image_file_frmat": "JPG",
        "image_potogrf_dt": "2021-11-22 16:40:03"
    },
    "annotations": {
        "antn_id": 3634097,
        "antn_ty": "POLYGON",
        "object_class_lclas_code": "01",
        "object_class_mlsft_code": "043",
        "object_class_sclas_code": "03",
        "object_class_lclas_nm": "목본",
        "object_class_mlsft_nm": "참가시나무",
        "object_class_sclas_nm": "열매",
        "pyn_xcrdnt": "1549,1605,1656,1719,1760,1833,1893,1940,1971,1994,2011,2025,2034,2044,2044,2031,2014,1989,1975,1943,1853,1739,1661,1548,1428,1330,1296,1223,1187,1163,1145,1126,1116,1126,1142,1156,1182,1203,1257,1284,1322,1391,1425,1481,1518",
        "pyn_ycrdnt": "887,884,894,907,925,964,1018,1064,1105,1141,1182,1227,1259,1333,1402,1481,1521,1571,1594,1638,1725,1776,1793,1786,1757,1709,1679,1606,1559,1522,1481,1403,1297,1246,1183,1142,1099,1059,1001,981,955,921,910,894,887"
    },
    "plants": {
        "wd_plnt_nm": "참가시나무",
        "scientific_nm": "Quercus salicina Blume, 1850.",
        "woody_herbal": "1",
        "edible_yn": "Y",
        "edible_part": "열매",
        "acquisition_term": "11월",
        "efficacy": "항염증|면역증진|항산화",
        "efficacy_ncl": "46.4|17.1|82.6",
        "nutrient": "15.4|15.2|15.5"
    },
    "ingredient": {
        "irdnt_nm": "Madecassoside|Ellagic acid|Quinic acid|2,3-(S)-hexahydroxydiphenoyl-D-glucose|3-O-Methylellagic acid|Ethyl caffeate|3,3-Di-O-methylellagic acid|Tianshic acid|2,3-(S)-hexahydroxydiphenoyl-D-glucose|Yamogenin acetate",
        "irdnt_ncl": "-1.4|0.2|-0.1|-0.2|-0.7|0.7|0.5|0.3|-0.7|1.7",
        "irdnt_chmcls_strct": " ",
        "irdnt_anals_instlm": "제주산학융합원"
    },
    "licenses": {
        "lcnse_nm": "CC-BY-SA"
    }
}